{
  "lastChecks": {
    "heartbeat": 1743743966,
    "git_status": 1743743966
  },
  "notes": "网络间歇性超时，2个仓库各有1 commit待推送",
  "lastUpdate": "2026-04-04 12:59",
  "pending": {
    "git_push": {
      "repos": [
        "ai-workspace-orchestrator (1 commit)",
        "romance-of-three-claws (1 commit)"
      ],
      "reason": "GitHub网络超时（RPC failed, curl 56）",
      "action": "等待网络稳定后自动重试或手动推送"
    }
  },
  "next_scheduled": {
    "awesome_ai_ideas_cleanup": "2026-04-05 09:00",
    "social_media_content": "2026-04-05 22:00"
  },
  "workspace_status": "clean and synced"
}
